LICENSE.txt
MANIFEST.in
README.rst
setup.py
jk_pwdinput/__init__.py
jk_pwdinput/pwdinput.py
jk_pwdinput.egg-info/PKG-INFO
jk_pwdinput.egg-info/SOURCES.txt
jk_pwdinput.egg-info/dependency_links.txt
jk_pwdinput.egg-info/not-zip-safe
jk_pwdinput.egg-info/requires.txt
jk_pwdinput.egg-info/top_level.txt