Metadata-Version: 1.1
Name: jk-pwdinput
Version: 0.2017.1.17
Summary: Provides the capability to read a passwords from STDIN. In contrast to typical password input in this case for every character pressed an asterisk is displayed.
Home-page: https://github.com/jkpubsrc/python-module-jk-pwdinput
Author: Jürgen Knauth
Author-email: pubsrc@binary-overflow.de
License: Apache 2.0
Download-URL: https://github.com/jkpubsrc/python-module-jk-pwdinput/tarball/0.2017.1.17
Keywords: password,security
Platform: UNKNOWN
Classifier: Development Status :: 5 - Production/Stable
Classifier: Programming Language :: Python :: 3.5
Classifier: License :: OSI Approved :: Apache Software License
